onelinevalidation/__init__.py
onelinevalidation/onelinevalidation.py
onelinevalidation-0.4.1.dist-info/LICENSE
onelinevalidation-0.4.1.dist-info/METADATA
onelinevalidation-0.4.1.dist-info/WHEEL
onelinevalidation-0.4.1.dist-info/top_level.txt
onelinevalidation-0.4.1.dist-info/RECORD
