Metadata-Version: 2.1
Name: onelinevalidation
Version: 0.4.1
Summary: onelinevalidation It is a simple library in the Python language that performs validate in an easy and simple way
Home-page: https://github.com/amr2018/onelinevalidation
Author: Amr Elgarhy
Author-email: amr.ee@yahoo.com
License: MIT
Platform: UNKNOWN
Classifier: License :: OSI Approved :: MIT License
Classifier: Programming Language :: Python
Classifier: Programming Language :: Python :: 3
Classifier: Programming Language :: Python :: 3.6
Classifier: Programming Language :: Python :: Implementation :: CPython
Classifier: Programming Language :: Python :: Implementation :: PyPy
Requires-Python: >=3.1.0
